open_agentinstruct/__init__.py
open_agentinstruct/cli.py
open_agentinstruct/agents/__init__.py
open_agentinstruct/agents/async_chat.py
open_agentinstruct/agents/content_transformation.py
open_agentinstruct/agents/instruction_generation.py
open_agentinstruct/agents/instruction_refinement.py
open_agentinstruct/agents/split_agents/content_generation/analytical_reasoning_content.json
open_agentinstruct/agents/split_agents/content_generation/brain_teaser_content.json
open_agentinstruct/agents/split_agents/content_generation/coding_content.json
open_agentinstruct/agents/split_agents/content_generation/conversation_content.json
open_agentinstruct/agents/split_agents/content_generation/creative_content_content.json
open_agentinstruct/agents/split_agents/content_generation/data_to_text_content.json
open_agentinstruct/agents/split_agents/content_generation/fermi_content.json
open_agentinstruct/agents/split_agents/content_generation/few_shot_reasoning_content.json
open_agentinstruct/agents/split_agents/content_generation/multiple_choice_question_content.json
open_agentinstruct/agents/split_agents/content_generation/open_domain_question_answering_content.json
open_agentinstruct/agents/split_agents/content_generation/rag_content.json
open_agentinstruct/agents/split_agents/content_generation/reading_comprehension_content.json
open_agentinstruct/agents/split_agents/content_generation/text_classification_content.json
open_agentinstruct/agents/split_agents/content_generation/text_extraction_content.json
open_agentinstruct/agents/split_agents/content_generation/text_modification_content.json
open_agentinstruct/agents/split_agents/content_generation/tool_use_content.json
open_agentinstruct/agents/split_agents/content_generation/web_agent_content.json
open_agentinstruct/agents/split_agents/instruction_generation/analytical_reasoning_instruction.json
open_agentinstruct/agents/split_agents/instruction_generation/brain_teaser_instruction.json
open_agentinstruct-0.1.0.dist-info/licenses/LICENSE
open_agentinstruct-0.1.0.dist-info/METADATA
open_agentinstruct-0.1.0.dist-info/WHEEL
open_agentinstruct-0.1.0.dist-info/entry_points.txt
open_agentinstruct-0.1.0.dist-info/top_level.txt
open_agentinstruct-0.1.0.dist-info/RECORD
