Metadata-Version: 2.4
Name: open-agentinstruct
Version: 0.1.0
Summary: A library for generating instruction-following data using agent-based workflows.
License: MIT License
Project-URL: Homepage, https://github.com/ThomasRochefortB/open-agentinstruct
Project-URL: Repository, https://github.com/ThomasRochefortB/open-agentinstruct
Classifier: Programming Language :: Python :: 3
Classifier: Programming Language :: Python :: 3.9
Classifier: Programming Language :: Python :: 3.10
Classifier: Programming Language :: Python :: 3.11
Classifier: License :: OSI Approved :: MIT License
Classifier: Operating System :: OS Independent
Classifier: Topic :: Scientific/Engineering :: Artificial Intelligence
Classifier: Topic :: Software Development :: Libraries :: Python Modules
Requires-Python: >=3.9
License-File: LICENSE
Requires-Dist: python-dotenv>=1.0.0
Requires-Dist: nest_asyncio>=1.5.0
Requires-Dist: aiohttp>=3.0.0
Requires-Dist: backoff
Requires-Dist: litellm>=1.35.0
Requires-Dist: datasets>=2.0.0
Requires-Dist: pdfminer.six>=20221105
Requires-Dist: setuptools
Provides-Extra: pdf
Requires-Dist: pdfminer.six>=20221105; extra == "pdf"
Provides-Extra: hf-datasets
Requires-Dist: datasets>=2.0.0; extra == "hf-datasets"
Provides-Extra: test
Requires-Dist: pytest>=7.0.0; extra == "test"
Provides-Extra: dev
Requires-Dist: pytest>=7.0.0; extra == "dev"
Requires-Dist: ruff; extra == "dev"
Requires-Dist: build; extra == "dev"
Requires-Dist: twine; extra == "dev"
Requires-Dist: pre-commit; extra == "dev"
Dynamic: license-file
